pyupgrade/__init__.py
pyupgrade/__main__.py
pyupgrade/_ast_helpers.py
pyupgrade/_data.py
pyupgrade/_main.py
pyupgrade/_string_helpers.py
pyupgrade/_token_helpers.py
pyupgrade/_plugins/__init__.py
pyupgrade/_plugins/collections_abc.py
pyupgrade/_plugins/constant_fold.py
pyupgrade/_plugins/datetime_utc_alias.py
pyupgrade/_plugins/default_encoding.py
pyupgrade/_plugins/defaultdict_lambda.py
pyupgrade/_plugins/dict_literals.py
pyupgrade/_plugins/exceptions.py
pyupgrade/_plugins/format_locals.py
pyupgrade/_plugins/fstrings.py
pyupgrade/_plugins/identity_equality.py
pyupgrade/_plugins/imports.py
pyupgrade/_plugins/io_open.py
pyupgrade/_plugins/legacy.py
pyupgrade/_plugins/lru_cache.py
pyupgrade/_plugins/metaclass_type.py
pyupgrade/_plugins/mock.py
pyupgrade/_plugins/native_literals.py
pyupgrade/_plugins/new_style_classes.py
pyupgrade/_plugins/open_mode.py
pyupgrade/_plugins/percent_format.py
pyupgrade/_plugins/set_literals.py
pyupgrade/_plugins/shlex_join.py
pyupgrade/_plugins/six_base_classes.py
pyupgrade/_plugins/six_calls.py
pyupgrade/_plugins/six_metaclasses.py
pyupgrade/_plugins/six_remove_decorators.py
pyupgrade/_plugins/six_simple.py
pyupgrade/_plugins/subprocess_run.py
pyupgrade/_plugins/type_of_primitive.py
pyupgrade/_plugins/typing_classes.py
pyupgrade/_plugins/typing_pep563.py
pyupgrade/_plugins/typing_pep585.py
pyupgrade/_plugins/typing_pep604.py
pyupgrade/_plugins/typing_pep646_unpack.py
pyupgrade/_plugins/typing_pep696_typevar_defaults.py
pyupgrade/_plugins/typing_text.py
pyupgrade/_plugins/unittest_aliases.py
pyupgrade/_plugins/unpack_list_comprehension.py
pyupgrade/_plugins/versioned_branches.py
pyupgrade-3.21.1.dist-info/LICENSE
pyupgrade-3.21.1.dist-info/METADATA
pyupgrade-3.21.1.dist-info/WHEEL
pyupgrade-3.21.1.dist-info/entry_points.txt
pyupgrade-3.21.1.dist-info/top_level.txt
pyupgrade-3.21.1.dist-info/RECORD
