Metadata-Version: 2.1
Name: pyupgrade
Version: 3.21.1
Summary: A tool to automatically upgrade syntax for newer versions.
Home-page: https://github.com/asottile/pyupgrade
Author: Anthony Sottile
Author-email: asottile@umich.edu
License: MIT
Classifier: Programming Language :: Python :: 3
Classifier: Programming Language :: Python :: 3 :: Only
Classifier: Programming Language :: Python :: Implementation :: CPython
Classifier: Programming Language :: Python :: Implementation :: PyPy
Requires-Python: >=3.10
License-File: LICENSE
Requires-Dist: tokenize-rt>=6.1.0
